setup.py
clicker/__init__.py
clicker/manage.py
clicker/settings.py
clicker/urls.py
clicker/classroomclicker/MessageListener.py
clicker/classroomclicker/MessagePublisher.py
clicker/classroomclicker/__init__.py
clicker/classroomclicker/models.py
clicker/classroomclicker/tests.py
clicker/classroomclicker/urls.py
clicker/classroomclicker/views.py
webservices_project3.egg-info/PKG-INFO
webservices_project3.egg-info/SOURCES.txt
webservices_project3.egg-info/dependency_links.txt
webservices_project3.egg-info/top_level.txt