Metadata-Version: 1.0
Name: webservices-project3
Version: 1.0
Summary: Final Project for Web Services
Home-page: http://www.luc.edu
Author: Utsav Pandey, Antonio Claros Molina
Author-email: upandey@luc.edu
License: UNKNOWN
Platform: UNKNOWN
